<?xml version="1.0" encoding="utf-8"?>
<puzzle>
    <resId>3002000034</resId>
    <version>1</version>
    <categoryID>1009</categoryID>
    <name>8格环绕</name>
    <iconPath>thumbnail</iconPath>
    <width>1500</width>
    <height>1500</height>
    <photoAmount>8</photoAmount>
    <formatAmount>1</formatAmount>
    <backgroundColor />
    <backgroundImagePath />
    <backgroundTile />
    <backgroundType>0</backgroundType>
    <bgBlurFilter />
    <bgFilterMaterialId />
    <photoPuzzlePieces>
        <photoPuzzle>
            <maskPath />
            <blurFilter />
            <filterMaterialId />
            <backgroundImagePath />
            <backgroundImageInnerFrame />
            <frameRectArray>
                <frameRect>{{1000,1000},{500,500}}</frameRect>
            </frameRectArray>
        </photoPuzzle>
        <photoPuzzle>
            <maskPath />
            <blurFilter />
            <filterMaterialId />
            <backgroundImagePath />
            <backgroundImageInnerFrame />
            <frameRectArray>
                <frameRect>{{500,1000},{500,500}}</frameRect>
            </frameRectArray>
        </photoPuzzle>
        <photoPuzzle>
            <maskPath />
            <blurFilter />
            <filterMaterialId />
            <backgroundImagePath />
            <backgroundImageInnerFrame />
            <frameRectArray>
                <frameRect>{{0,1000},{500,500}}</frameRect>
            </frameRectArray>
        </photoPuzzle>
        <photoPuzzle>
            <maskPath />
            <blurFilter />
            <filterMaterialId />
            <backgroundImagePath />
            <backgroundImageInnerFrame />
            <frameRectArray>
                <frameRect>{{1000,500},{500,500}}</frameRect>
            </frameRectArray>
        </photoPuzzle>
        <photoPuzzle>
            <maskPath />
            <blurFilter />
            <filterMaterialId />
            <backgroundImagePath />
            <backgroundImageInnerFrame />
            <frameRectArray>
                <frameRect>{{0,500},{500,500}}</frameRect>
            </frameRectArray>
        </photoPuzzle>
        <photoPuzzle>
            <maskPath />
            <blurFilter />
            <filterMaterialId />
            <backgroundImagePath />
            <backgroundImageInnerFrame />
            <frameRectArray>
                <frameRect>{{1000,0},{500,500}}</frameRect>
            </frameRectArray>
        </photoPuzzle>
        <photoPuzzle>
            <maskPath />
            <blurFilter />
            <filterMaterialId />
            <backgroundImagePath />
            <backgroundImageInnerFrame />
            <frameRectArray>
                <frameRect>{{500,0},{500,500}}</frameRect>
            </frameRectArray>
        </photoPuzzle>
        <photoPuzzle>
            <maskPath />
            <blurFilter />
            <filterMaterialId />
            <backgroundImagePath />
            <backgroundImageInnerFrame />
            <frameRectArray>
                <frameRect>{{0,0},{500,500}}</frameRect>
            </frameRectArray>
        </photoPuzzle>
    </photoPuzzlePieces>
    <imagePuzzlePieces>
        <imagePuzzle>
            <type>0</type>
            <imagePath>img.post</imagePath>
            <weatherColor />
            <frameRectArray>
                <frameRect>{{0,0},{1500,1500}}</frameRect>
            </frameRectArray>
        </imagePuzzle>
    </imagePuzzlePieces>
    <textPuzzlePieces />
    <activity>
        <sina />
        <expired />
    </activity>
</puzzle>
